{
  "updated": "2026-07-15T07:28:19+09:00",
  "source": "DART",
  "items": [
    {
      "name": "경농",
      "code": "002100",
      "exDate": "2026-06-30",
      "payDate": "2026-07-14",
      "amount": 250,
      "market": "KOSPI"
    },
    {
      "name": "더즌",
      "code": "462860",
      "exDate": "2026-06-30",
      "payDate": "2026-07-22",
      "amount": 15,
      "market": "KOSDAQ"
    },
    {
      "name": "미원에스씨",
      "code": "268280",
      "exDate": "2026-06-30",
      "payDate": "2026-07-24",
      "amount": 1200,
      "market": "KOSPI"
    },
    {
      "name": "미원홀딩스",
      "code": "107590",
      "exDate": "2026-06-30",
      "payDate": "2026-07-24",
      "amount": 1200,
      "market": "KOSPI"
    },
    {
      "name": "미원화학",
      "code": "134380",
      "exDate": "2026-06-30",
      "payDate": "2026-07-24",
      "amount": 250,
      "market": "KOSPI"
    },
    {
      "name": "셀로맥스사이언스",
      "code": "471820",
      "exDate": "2026-06-30",
      "payDate": "2026-07-30",
      "amount": 50,
      "market": "KOSDAQ"
    },
    {
      "name": "슈프리마",
      "code": "236200",
      "exDate": "2026-06-30",
      "payDate": "2026-07-23",
      "amount": 200,
      "market": "KOSDAQ"
    },
    {
      "name": "슈프리마에이치큐",
      "code": "094840",
      "exDate": "2026-06-30",
      "payDate": "2026-07-23",
      "amount": 100,
      "market": "KOSDAQ"
    },
    {
      "name": "크레버스",
      "code": "096240",
      "exDate": "2026-06-30",
      "payDate": "2026-07-08",
      "amount": 500,
      "market": "KOSDAQ"
    },
    {
      "name": "에이블씨엔씨",
      "code": "078520",
      "exDate": "2026-07-15",
      "payDate": "2026-07-29",
      "amount": 100,
      "market": "KOSPI"
    },
    {
      "name": "동남합성",
      "code": "023450",
      "exDate": "2026-07-24",
      "payDate": "2026-08-14",
      "amount": 650,
      "market": "KOSPI"
    },
    {
      "name": "미원홀딩스",
      "code": "107590",
      "exDate": "2026-07-24",
      "payDate": "2026-08-14",
      "amount": 650,
      "market": "KOSPI"
    },
    {
      "name": "케이씨씨글라스",
      "code": "344820",
      "exDate": "2026-07-24",
      "payDate": "2026-07-10",
      "amount": 600,
      "market": "KOSPI"
    },
    {
      "name": "위드텍",
      "code": "348350",
      "exDate": "2026-07-29",
      "payDate": "2026-08-11",
      "amount": 800,
      "market": "KOSDAQ"
    },
    {
      "name": "이노테나",
      "code": "333050",
      "exDate": "2026-07-29",
      "payDate": "2026-08-20",
      "amount": 20,
      "market": "KOSDAQ"
    },
    {
      "name": "케이티",
      "code": "030200",
      "exDate": "2026-07-29",
      "payDate": "2026-08-13",
      "amount": 600,
      "market": "KOSPI"
    },
    {
      "name": "E1",
      "code": "017940",
      "exDate": "2026-07-31",
      "payDate": "2026-08-14",
      "amount": 450,
      "market": "KOSPI"
    },
    {
      "name": "기업은행",
      "code": "024110",
      "exDate": "2026-07-31",
      "payDate": "2026-08-28",
      "amount": 210,
      "market": "KOSPI"
    },
    {
      "name": "매드업",
      "code": "0039P0",
      "exDate": "2026-07-31",
      "payDate": "2026-08-07",
      "amount": 54,
      "market": "KOSDAQ"
    },
    {
      "name": "매드업",
      "code": "0039P0",
      "exDate": "2026-07-31",
      "payDate": "2026-08-07",
      "amount": 54,
      "market": "KOSDAQ"
    }
  ]
}
